cnd_event_logger/VERSION
cnd_event_logger/__init__.py
cnd_event_logger/__version__.py
cnd_event_logger/cnd_base.py
cnd_event_logger/cnd_event.py
cnd_event_logger/cnd_inventory.py
cnd_event_logger-0.1.3.dist-info/METADATA
cnd_event_logger-0.1.3.dist-info/WHEEL
cnd_event_logger-0.1.3.dist-info/top_level.txt
cnd_event_logger-0.1.3.dist-info/RECORD
