Metadata-Version: 2.1
Name: cnd-event-logger
Version: 0.1.3
Summary: The definitive tools to log event when you build IaaS
Home-page: https://changendevops.com
Author: Denis FABIEN
Author-email: denis.fabien@changendevops.com
License: MIT/X11
Project-URL: Documentation, https://changendevops.com
Project-URL: Source, https://gitlab.com/changendevops/iaasinventory/cndeventlogger.git
Classifier: License :: OSI Approved :: MIT License
Classifier: Operating System :: OS Independent
Requires-Dist: expects
Requires-Dist: mockito
Requires-Dist: python-consul
Requires-Dist: pyyaml
Requires-Dist: cndprint
Requires-Dist: mamba
Requires-Dist: twine
